tests/__init__.py
tests/conftest.py
tests/session_pool.py
tests/test_disable_discovery.py
tests/test_errors.py
tests/aio/__init__.py
tests/aio/test_async_iter_stream.py
tests/aio/test_connection.py
tests/aio/test_connection_pool.py
tests/aio/test_credentials.py
tests/aio/test_session_pool.py
tests/aio/test_table.py
tests/aio/test_table_client.py
tests/aio/test_tx.py
tests/aio/test_types.py
tests/aio/query/__init__.py
tests/aio/query/conftest.py
tests/aio/query/test_query_session.py
tests/aio/query/test_query_session_pool.py
tests/aio/query/test_query_transaction.py
tests/auth/__init__.py
tests/auth/test_credentials.py
tests/auth/test_static_credentials.py
tests/coordination/__init__.py
tests/coordination/test_coordination_client.py
tests/iam/__init__.py
tests/iam/test_auth.py
tests/oauth2_token_exchange/__init__.py
tests/oauth2_token_exchange/test_token_exchange.py
tests/oauth2_token_exchange/test_token_source.py
tests/query/__init__.py
tests/query/conftest.py
tests/query/test_query_client_settings.py
tests/query/test_query_parameters.py
tests/query/test_query_session.py
tests/query/test_query_session_pool.py
tests/query/test_query_transaction.py
tests/query/test_types.py
tests/ssl/__init__.py
tests/ssl/test_ssl.py
tests/table/__init__.py
tests/table/table_test.py
tests/table/test_table_client.py
tests/table/test_tx.py
tests/topics/__init__.py
tests/topics/test_control_plane.py
tests/topics/test_topic_reader.py
tests/topics/test_topic_transactions.py
tests/topics/test_topic_writer.py
ydb/__init__.py
ydb/_apis.py
ydb/_constants.py
ydb/_errors.py
ydb/_session_impl.py
ydb/_sp_impl.py
ydb/_tx_ctx_impl.py
ydb/_utilities.py
ydb/_utilities_test.py
ydb/auth_helpers.py
ydb/connection.py
ydb/convert.py
ydb/credentials.py
ydb/default_pem.py
ydb/driver.py
ydb/export.py
ydb/global_settings.py
ydb/import_client.py
ydb/interceptor.py
ydb/issues.py
ydb/operation.py
ydb/pool.py
ydb/resolver.py
ydb/retries.py
ydb/scheme.py
ydb/scheme_test.py
ydb/scripting.py
ydb/settings.py
ydb-3.23.0.dist-info/AUTHORS
ydb-3.23.0.dist-info/LICENSE
ydb-3.23.0.dist-info/METADATA
ydb-3.23.0.dist-info/WHEEL
ydb-3.23.0.dist-info/top_level.txt
ydb-3.23.0.dist-info/RECORD
