Metadata-Version: 2.1
Name: ydb
Version: 3.23.0
Summary: YDB Python SDK
Home-page: http://github.com/ydb-platform/ydb-python-sdk
Author: Yandex LLC
Author-email: ydb@yandex-team.ru
License: Apache 2.0
Classifier: Programming Language :: Python
Classifier: Programming Language :: Python :: 2
Classifier: Programming Language :: Python :: 2.7
Classifier: Programming Language :: Python :: 3
Classifier: Programming Language :: Python :: 3.6
License-File: LICENSE
License-File: AUTHORS
Requires-Dist: grpcio>=1.42.0
Requires-Dist: packaging
Requires-Dist: protobuf<6.0.0,>=3.13.0
Requires-Dist: aiohttp<4
Provides-Extra: yc
Requires-Dist: yandexcloud; extra == "yc"
